sandlersteam/__init__.py
sandlersteam/cli.py
sandlersteam/satd.py
sandlersteam/state.py
sandlersteam/unsatd.py
sandlersteam/resources/data/SandlerSatdSteamTableP1.txt
sandlersteam/resources/data/SandlerSatdSteamTableP2.txt
sandlersteam/resources/data/SandlerSatdSteamTableT1.txt
sandlersteam/resources/data/SandlerSatdSteamTableT2.txt
sandlersteam/resources/data/SandlerSubcSteamTables.txt
sandlersteam/resources/data/SandlerSuphSteamTables.txt
sandlersteam-0.9.0.dist-info/METADATA
sandlersteam-0.9.0.dist-info/WHEEL
sandlersteam-0.9.0.dist-info/entry_points.txt
sandlersteam-0.9.0.dist-info/licenses/LICENSE
sandlersteam-0.9.0.dist-info/RECORD
